Workbook

Sheet sales_data
A1: Order_ID | B1: Order_Date | C1: Customer_ID | D1: Customer_Name | E1: City | F1: Region | G1: Category | H1: Product | I1: Quantity | J1: Unit_Price | K1: Discount_Percent | L1: Unit_Cost | M1: Segment | N1: Sales | O1: Profit | P1: Total sales | Q1: Total profit
A2: SO0001 | B2: 45747 | C2: C0139 | D2: Customer 170 | E2: Delhi | F2: North | G2: Home & Kitchen | H2: Bedsheet | I2: 3 | J2: 1200 | K2: 0.05 | L2: 350 | M2: Consumer | N2: =I2*J2*(1-K2) -> 3420 | O2: =N2-(L2*I2) -> 2370 | P2: =SUM(N2:N501) -> 9800307.5 | Q2: =SUM(O2:O501) -> 7532097.5
A3: SO0002 | B3: 45914 | C3: C0082 | D3: Customer 164 | E3: Kolkata | F3: South | G3: Furniture | H3: Sofa | I3: 4 | J3: 22000 | K3: 0.05 | L3: 5000 | M3: Home Office | N3: =I3*J3*(1-K3) -> 83600 | O3: =N3-(L3*I3) -> 63600 | P3: =SUM(N3:N502) -> 9796887.5 | Q3: =SUM(O3:O502) -> 7529727.5
A4: SO0003 | B4: 46019 | C4: C0137 | D4: Customer 144 | E4: Mumbai | F4: East | G4: Electronics | H4: Smartphone | I4: 2 | J4: 18000 | K4: 0 | L4: 3000 | M4: Home Office | N4: =I4*J4*(1-K4) -> 36000 | O4: =N4-(L4*I4) -> 30000 | P4: =SUM(N4:N503) -> 9713287.5 | Q4: =SUM(O4:O503) -> 7466127.5
A5: SO0004 | B5: 45699 | C5: C0130 | D5: Customer 122 | E5: Chennai | F5: West | G5: Electronics | H5: Laptop | I5: 3 | J5: 52000 | K5: 0.1 | L5: 9000 | M5: Home Office | N5: =I5*J5*(1-K5) -> 140400 | O5: =N5-(L5*I5) -> 113400 | P5: =SUM(N5:N504) -> 9677287.5 | Q5: =SUM(O5:O504) -> 7436127.5
A6: SO0005 | B6: 45950 | C6: C0014 | D6: Customer 091 | E6: Hyderabad | F6: West | G6: Clothing | H6: T-Shirt | I6: 4 | J6: 550 | K6: 0.05 | L6: 180 | M6: Corporate | N6: =I6*J6*(1-K6) -> 2090 | O6: =N6-(L6*I6) -> 1370 | P6: =SUM(N6:N505) -> 9536887.5 | Q6: =SUM(O6:O505) -> 7322727.5
A7: SO0006 | B7: 45943 | C7: C0055 | D7: Customer 064 | E7: Pune | F7: North | G7: Electronics | H7: Keyboard | I7: 2 | J7: 950 | K7: 0 | L7: 300 | M7: Corporate | N7: =I7*J7*(1-K7) -> 1900 | O7: =N7-(L7*I7) -> 1300 | P7: =SUM(N7:N506) -> 9534797.5 | Q7: =SUM(O7:O506) -> 7321357.5
A8: SO0007 | B8: 45942 | C8: C0137 | D8: Customer 142 | E8: Chennai | F8: East | G8: Electronics | H8: Headphones | I8: 2 | J8: 1800 | K8: 0.15 | L8: 650 | M8: Home Office | N8: =I8*J8*(1-K8) -> 3060 | O8: =N8-(L8*I8) -> 1760 | P8: =SUM(N8:N507) -> 9532897.5 | Q8: =SUM(O8:O507) -> 7320057.5
A9: SO0008 | B9: 45828 | C9: C0025 | D9: Customer 148 | E9: Delhi | F9: East | G9: Clothing | H9: Sneakers | I9: 3 | J9: 2600 | K9: 0 | L9: 800 | M9: Consumer | N9: =I9*J9*(1-K9) -> 7800 | O9: =N9-(L9*I9) -> 5400 | P9: =SUM(N9:N508) -> 9529837.5 | Q9: =SUM(O9:O508) -> 7318297.5
A10: SO0009 | B10: 45797 | C10: C0122 | D10: Customer 163 | E10: Hyderabad | F10: South | G10: Electronics | H10: Headphones | I10: 1 | J10: 1800 | K10: 0.1 | L10: 650 | M10: Corporate | N10: =I10*J10*(1-K10) -> 1620 | O10: =N10-(L10*I10) -> 970 | P10: =SUM(N10:N509) -> 9522037.5 | Q10: =SUM(O10:O509) -> 7312897.5
A11: SO0010 | B11: 45975 | C11: C0145 | D11: Customer 135 | E11: Chennai | F11: West | G11: Clothing | H11: T-Shirt | I11: 4 | J11: 550 | K11: 0 | L11: 180 | M11: Corporate | N11: =I11*J11*(1-K11) -> 2200 | O11: =N11-(L11*I11) -> 1480 | P11: =SUM(N11:N510) -> 9520417.5 | Q11: =SUM(O11:O510) -> 7311927.5
A12: SO0011 | B12: 45735 | C12: C0174 | D12: Customer 029 | E12: Mumbai | F12: North | G12: Home & Kitchen | H12: Cookware Set | I12: 2 | J12: 2400 | K12: 0.05 | L12: 650 | M12: Home Office | N12: =I12*J12*(1-K12) -> 4560 | O12: =N12-(L12*I12) -> 3260 | P12: =SUM(N12:N511) -> 9518217.5 | Q12: =SUM(O12:O511) -> 7310447.5
A13: SO0012 | B13: 45740 | C13: C0108 | D13: Customer 024 | E13: Delhi | F13: East | G13: Clothing | H13: Sneakers | I13: 3 | J13: 2600 | K13: 0 | L13: 800 | M13: Home Office | N13: =I13*J13*(1-K13) -> 7800 | O13: =N13-(L13*I13) -> 5400 | P13: =SUM(N13:N512) -> 9513657.5 | Q13: =SUM(O13:O512) -> 7307187.5
... A501: SO0500 | B501: 45877 | C501: C0098 | D501: Customer 163 | E501: Chennai | F501: East | G501: Electronics | H501: Laptop | I501: 1 | J501: 52000 | K501: 0.05 | L501: 9000 | M501: Corporate | N501: =I501*J501*(1-K501) -> 49400 | O501: =N501-(L501*I501) -> 40400 | P501: =SUM(N501:N1000) -> 49400 | Q501: =SUM(O501:O1000) -> 40400

Sheet KPI_Summary
A1: KPI Name | B1: KPI Value
A2: Total Sales | B2: =SUM(sales_data!N2:N501) -> 9800307.5
A3: Total Profit | B3: =SUM(sales_data!O2:O501) -> 7532097.5
A4: Total Orders | B4: =COUNTA(sales_data!A2:A501) -> 500
A5: Total Quantity | B5: =SUM(sales_data!I2:I501) -> 1467
A6: Average Sales | B6: =AVERAGE(sales_data!N2:N501) -> 19600.615

Sheet pivot tables
A3: Row Labels | B3: Sum of Sales | E3: Row Labels | F3: Sum of Sales | H3: Row Labels | I3: Sum of Sales
A4: East | B4: 2877502.5 | E4: Clothing | F4: 638685 | H4: 2025 | I4: 9800307.5
A5: North | B5: 2120027.5 | E5: Electronics | F5: 4477230 | H5: Jan | I5: 710787.5
A6: South | B6: 1845167.5 | E6: Furniture | F6: 4173200 | H6: Feb | I6: 689825
A7: West | B7: 2957610 | E7: Home & Kitchen | F7: 511192.5 | H7: Mar | I7: 1018080
A8: Grand Total | B8: 9800307.5 | E8: Grand Total | F8: 9800307.5 | H8: Apr | I8: 638047.5
H9: May | I9: 650345
H10: Jun | I10: 554745
H11: Jul | I11: 1317427.5
H12: Aug | I12: 695315
H13: Sep | I13: 678215
H14: Oct | I14: 928157.5
H15: Nov | I15: 606377.5
H16: Dec | I16: 1312985
H17: Grand Total | I17: 9800307.5

Sheet Charts

Sheet Dashboard
A1: SALES DATA ANALYSIS DASHBOARD
A3: Total Sales | C3: Total Profit | E3: Total Orders | G3: Total Quantity | I3: Average Sales
A4: =KPI_Summary!B2 -> 9800307.5 | C4: =KPI_Summary!B3 -> 7532097.5 | E4: =KPI_Summary!B4 -> 500 | G4: =KPI_Summary!B5 -> 1467 | I4: =KPI_Summary!B6 -> 19600.615
